apb/__init__.py
apb/_test_pointer.py
apb/application/__init__.py
apb/application/foldseek/__init__.py
apb/application/foldseek/align.py
apb/application/foldseek/base.py
apb/application/foldseek/datatypes.py
apb/application/foldseek/test_align.py
apb/application/foldseek/test_base.py
apb/application/foldseek/utils.py
apb/application/tmalign/__init__.py
apb/application/tmalign/align.py
apb/application/tmalign/core.py
apb/application/tmalign/test_align.py
apb/application/tmalign/test_core.py
apb/config.py
apb/database/collection/__init__.py
apb/database/collection/interface.py
apb/database/collection/schema.py
apb/database/collection/test_interface.py
apb/database/test_utils.py
apb/database/utils.py
apb/profile.py
apb/sequence/__init__.py
apb/sequence/test_utils.py
apb/sequence/utils.py
apb/structure/__init__.py
apb/structure/convert.py
apb/structure/features/__init__.py
apb/structure/features/accessibility/__init__.py
apb/structure/features/accessibility/core.py
apb/structure/features/accessibility/datatypes.py
apb/structure/features/accessibility/normalization.py
apb/structure/features/accessibility/test_accessibility.py
apb/structure/features/secondary_structure.py
apb/structure/features/test_secondary_structure.py
apb/structure/fold_server.py
apb/structure/test_convert.py
apb/structure/test_utils.py
apb/structure/utils.py
apb/test_profile.py
apb/test_utils.py
apb/types.py
apb/utils.py
apb/vendor/strenum.py
apb/workflow/__init__.py
apb/workflow/align_to_reference.py
apb/workflow/create_collection.py
apb/workflow/test_create_collection.py
arcadia_apb-0.2.2.dist-info/LICENSE
arcadia_apb-0.2.2.dist-info/METADATA
arcadia_apb-0.2.2.dist-info/WHEEL
arcadia_apb-0.2.2.dist-info/entry_points.txt
arcadia_apb-0.2.2.dist-info/RECORD
