Metadata-Version: 2.3
Name: arcadia-apb
Version: 0.2.2
Summary: General purpose toolkit for applied protein biology.
License: MIT
Author: Evan Kiefl
Author-email: evan.kiefl@arcadiascience.com
Requires-Python: >=3.10,<4.0
Classifier: License :: OSI Approved :: MIT License
Classifier: Programming Language :: Python :: 3
Classifier: Programming Language :: Python :: 3.10
Classifier: Programming Language :: Python :: 3.11
Classifier: Programming Language :: Python :: 3.12
Classifier: Programming Language :: Python :: 3.13
Requires-Dist: aiohttp (>=3.11.18,<4.0.0)
Requires-Dist: arcadia-pycolor (>=0.5.1)
Requires-Dist: attrs (>=21.3.0)
Requires-Dist: biotite (>=1.0)
Requires-Dist: bottleneck (>=1.4.0)
Requires-Dist: cattrs (>=22.1.0)
Requires-Dist: click (>=8.0.0)
Requires-Dist: dask[distributed] (>=2024.6.2)
Requires-Dist: netcdf4 (>=1.6.5)
Requires-Dist: numpy (>=2.0)
Requires-Dist: pandas (>=2.0)
Requires-Dist: pandera (>=0.20)
Requires-Dist: plotly (>=5.22.0)
Requires-Dist: python-slugify (>=8.0.4,<9.0.0)
Requires-Dist: rich (>=13.7.1)
Requires-Dist: scipy (>=1.13)
Requires-Dist: sqlalchemy (>=2.0.30)
Requires-Dist: sqlalchemy-utils (>=0.41.2)
Requires-Dist: typer (>=0.15.4,<0.16.0)
Requires-Dist: xarray (>=2024.6.0)
Project-URL: Documentation, https://github.com/Arcadia-Science/applied-protein-biology-toolkit
Project-URL: Homepage, https://github.com/Arcadia-Science/applied-protein-biology-toolkit
Project-URL: Repository, https://github.com/Arcadia-Science/applied-protein-biology-toolkit
